odoo/addons/mrp_subcontracting/README.rst
odoo/addons/mrp_subcontracting/__init__.py
odoo/addons/mrp_subcontracting/__manifest__.py
odoo/addons/mrp_subcontracting/hooks.py
odoo/addons/mrp_subcontracting/data/mrp_subcontracting_data.xml
odoo/addons/mrp_subcontracting/data/mrp_subcontracting_demo.xml
odoo/addons/mrp_subcontracting/i18n/ar.po
odoo/addons/mrp_subcontracting/i18n/az.po
odoo/addons/mrp_subcontracting/i18n/az_AZ.po
odoo/addons/mrp_subcontracting/i18n/bg.po
odoo/addons/mrp_subcontracting/i18n/cs.po
odoo/addons/mrp_subcontracting/i18n/da.po
odoo/addons/mrp_subcontracting/i18n/de.po
odoo/addons/mrp_subcontracting/i18n/el.po
odoo/addons/mrp_subcontracting/i18n/es.po
odoo/addons/mrp_subcontracting/i18n/fi.po
odoo/addons/mrp_subcontracting/i18n/fr.po
odoo/addons/mrp_subcontracting/i18n/he.po
odoo/addons/mrp_subcontracting/i18n/hr.po
odoo/addons/mrp_subcontracting/i18n/hu.po
odoo/addons/mrp_subcontracting/i18n/id.po
odoo/addons/mrp_subcontracting/i18n/it.po
odoo/addons/mrp_subcontracting/i18n/ja.po
odoo/addons/mrp_subcontracting/i18n/ko.po
odoo/addons/mrp_subcontracting/i18n/lb.po
odoo/addons/mrp_subcontracting/i18n/lt.po
odoo/addons/mrp_subcontracting/i18n/lv.po
odoo/addons/mrp_subcontracting/i18n/ml.po
odoo/addons/mrp_subcontracting/i18n/mn.po
odoo/addons/mrp_subcontracting/i18n/mrp_subcontracting.pot
odoo/addons/mrp_subcontracting/i18n/my.po
odoo/addons/mrp_subcontracting/i18n/nb.po
odoo/addons/mrp_subcontracting/i18n/nl.po
odoo/addons/mrp_subcontracting/i18n/pl.po
odoo/addons/mrp_subcontracting/i18n/pt.po
odoo/addons/mrp_subcontracting/i18n/pt_BR.po
odoo/addons/mrp_subcontracting/i18n/ro.po
odoo/addons/mrp_subcontracting/i18n/ru.po
odoo/addons/mrp_subcontracting/i18n/sk.po
odoo/addons/mrp_subcontracting/i18n/sl.po
odoo/addons/mrp_subcontracting/i18n/sr.po
odoo/addons/mrp_subcontracting/i18n/sv.po
odoo/addons/mrp_subcontracting/i18n/th.po
odoo/addons/mrp_subcontracting/i18n/tr.po
odoo/addons/mrp_subcontracting/i18n/uk.po
odoo12_addon_mrp_subcontracting-12.0.1.0.6.dist-info/METADATA
odoo12_addon_mrp_subcontracting-12.0.1.0.6.dist-info/WHEEL
odoo12_addon_mrp_subcontracting-12.0.1.0.6.dist-info/top_level.txt
odoo12_addon_mrp_subcontracting-12.0.1.0.6.dist-info/RECORD
